CTL/__init__.py
CTL/_tree.py
CTL/causal_learn_forest.py
CTL/causal_tree_learn.py
CTL/causal_tree_match.py
CTL/pehe_tree.py
CTL/sig_diff_tree.py
CTL/tree.py
CTL/causal_tree/__init__.py
CTL/causal_tree/ct.py
CTL/causal_tree/util.py
CTL/causal_tree/util_c.c
CTL/causal_tree/util_c.cpython-310-darwin.so
CTL/causal_tree/util_c.pyx
CTL/causal_tree/ctl/__init__.py
CTL/causal_tree/ctl/adaptive.py
CTL/causal_tree/ctl/binary_ctl.py
CTL/causal_tree/ctl/ctl_base.py
CTL/causal_tree/ctl/ctl_honest.py
CTL/causal_tree/ctl/ctl_val_honest.py
CTL/causal_tree/ctl/honest.py
CTL/causal_tree/ctl_match/__init__.py
CTL/causal_tree/ctl_match/binary_ctl.py
CTL/causal_tree/ctl_match/ctl_base.py
CTL/causal_tree/ctl_trigger/__init__.py
CTL/causal_tree/ctl_trigger/adaptive_trigger.py
CTL/causal_tree/ctl_trigger/ctl_base_trigger.py
CTL/causal_tree/ctl_trigger/ctl_honest_trigger.py
CTL/causal_tree/ctl_trigger/ctl_val_honest_trigger.py
CTL/causal_tree/ctl_trigger/honest_trigger.py
CTL/causal_tree/ctl_trigger/trigger_ctl.py
CTL/causal_tree/nn_pehe/__init__.py
CTL/causal_tree/nn_pehe/balance_split.py
CTL/causal_tree/nn_pehe/base.py
CTL/causal_tree/nn_pehe/honest.py
CTL/causal_tree/nn_pehe/tree.py
CTL/causal_tree/nn_pehe/val.py
CTL/causal_tree/r_tree/__init__.py
CTL/causal_tree/r_tree/base.py
CTL/causal_tree/r_tree/tree.py
CTL/causal_tree/sig_diff/__init__.py
CTL/causal_tree/sig_diff/sig.py
CTL/causal_tree/sig_diff/sig_base.py
CTL/causal_tree/sig_diff/sig_val.py
causal_tree_learn-2.43.dist-info/LICENSE
causal_tree_learn-2.43.dist-info/METADATA
causal_tree_learn-2.43.dist-info/WHEEL
causal_tree_learn-2.43.dist-info/top_level.txt
causal_tree_learn-2.43.dist-info/RECORD
