Metadata-Version: 2.1
Name: causal-tree-learn
Version: 2.43
Summary: Python implementation of causal trees with validation
Home-page: https://github.com/edgeslab/CTL
Author: Christopher Tran
Author-email: ctran29@uic.edu
Classifier: Programming Language :: Python :: 3
Classifier: License :: OSI Approved :: MIT License
Classifier: Operating System :: OS Independent
Requires-Python: >=3.6
License-File: LICENSE
Requires-Dist: numpy
Requires-Dist: scikit-learn
Requires-Dist: scipy
